{
  "todo": [
    {
      "id": 1,
      "title": "json-server",
      "status": false
    },
    {
      "title": "coding",
      "status": false,
      "id": 2
    },
    {
      "title": "sasa",
      "status": false,
      "id": 3
    },
    {
      "title": "play",
      "status": false,
      "id": 4
    },
    {
      "title": "reading",
      "status": false,
      "id": 5
    },
    {
      "title": "cooking",
      "status": false,
      "id": 6
    },
    {
      "title": "ss",
      "status": false,
      "id": 7
    },
    {
      "title": "fdsdf",
      "status": false,
      "id": 8
    },
    {
      "title": "sadf",
      "status": false,
      "id": 9
    },
    {
      "title": "fasdfsadf",
      "status": false,
      "id": 10
    },
    {
      "title": "sar",
      "status": false,
      "id": 11
    }
  ]
}